ulozto_search/__init__.py
ulozto_search/__main__.py
ulozto_search/ulozto_search.py
ulozto_search-1.0.4.dist-info/LICENSE
ulozto_search-1.0.4.dist-info/METADATA
ulozto_search-1.0.4.dist-info/WHEEL
ulozto_search-1.0.4.dist-info/entry_points.txt
ulozto_search-1.0.4.dist-info/top_level.txt
ulozto_search-1.0.4.dist-info/RECORD
