Metadata-Version: 2.1
Name: ulozto-search
Version: 1.0.4
Summary: Python package to query uloz.to
Home-page: https://github.com/ZDVokoun/ulozto-search
Author: ZDVokoun
Author-email: grebe_hygrology@aleeas.com
License: UNKNOWN
Project-URL: Bug Reports, https://github.com/ZDVokoun/ulozto-search/issues
Project-URL: Source, https://github.com/ZDVokoun/ulozto-search
Platform: UNKNOWN
Classifier: License :: OSI Approved :: MIT License
Classifier: Programming Language :: Python :: 3
Requires-Python: >=3.6, <4
License-File: LICENSE
Requires-Dist: requests
Requires-Dist: beautifulsoup4
